ellar_throttler/__init__.py
ellar_throttler/constants.py
ellar_throttler/decorators.py
ellar_throttler/exception.py
ellar_throttler/module.py
ellar_throttler/py.typed
ellar_throttler/throttler_interceptor.py
ellar_throttler/throttler_module_options.py
ellar_throttler/throttler_service.py
ellar_throttler/throttler_storage_options.py
ellar_throttler/throttler_storage_record.py
ellar_throttler/interfaces/__init__.py
ellar_throttler/interfaces/throttler.py
ellar_throttler/interfaces/throttler_storage.py
ellar_throttler/model/__init__.py
ellar_throttler/model/anonymous.py
ellar_throttler/model/base.py
ellar_throttler/model/http.py
ellar_throttler/model/user.py
ellar_throttler/model/websocket.py
ellar_throttler-0.1.7.dist-info/WHEEL
ellar_throttler-0.1.7.dist-info/METADATA
ellar_throttler-0.1.7.dist-info/RECORD
