Metadata-Version: 2.1
Name: ellar-throttler
Version: 0.1.7
Summary: A rate limiting module for Ellar
Author-email: Ezeudoh Tochukwu <tochukwu.ezeudoh@gmail.com>
Requires-Python: >=3.8
Classifier: Intended Audience :: Information Technology
Classifier: Intended Audience :: System Administrators
Classifier: Operating System :: OS Independent
Classifier: Topic :: Internet
Classifier: Topic :: Software Development :: Libraries :: Application Frameworks
Classifier: Topic :: Software Development :: Libraries :: Python Modules
Classifier: Topic :: Software Development :: Libraries
Classifier: Topic :: Software Development
Classifier: Typing :: Typed
Classifier: Environment :: Web Environment
Classifier: Intended Audience :: Developers
Classifier: License :: OSI Approved :: MIT License
Classifier: Programming Language :: Python :: 3
Classifier: Programming Language :: Python :: 3.8
Classifier: Programming Language :: Python :: 3.9
Classifier: Programming Language :: Python :: 3.10
Classifier: Programming Language :: Python :: 3.11
Classifier: Programming Language :: Python :: 3 :: Only
Classifier: Framework :: AsyncIO
Classifier: Topic :: Internet :: WWW/HTTP :: HTTP Servers
Classifier: Topic :: Internet :: WWW/HTTP
Requires-Dist: ellar >= 0.8.2
Project-URL: Bug Tracker, https://github.com/python-ellar/ellar-throttler/issues
Project-URL: Documentation, https://python-ellar.github.io/ellar-throttler/
Project-URL: Homepage, https://github.com/python-ellar/ellar-throttler
Project-URL: Source, https://github.com/python-ellar/ellar-throttler
